{
  "parent": "rfmod:rf_ingot",
  "display": {
    "icon": {
      "item": "rfmod:rf_chestplate",
      "nbt": "{Damage:0}"
    },
    "title": {
      "translate": "One of us"
    },
    "description": {
      "translate": "Dress yourself like a RF member"
    },
    "frame": "goal",
    "show_toast": true,
    "announce_to_chat": true,
    "hidden": false
  },
  "criteria": {
    "diamond_helmet": {
      "trigger": "minecraft:inventory_changed",
      "conditions": {
        "items": [
          {
            "item": "rfmod:rf_helmet"
          }
        ]
      }
    },
    "diamond_chestplate": {
      "trigger": "minecraft:inventory_changed",
      "conditions": {
        "items": [
          {
            "item": "rfmod:rf_chestplate"
          }
        ]
      }
    },
    "diamond_leggings": {
      "trigger": "minecraft:inventory_changed",
      "conditions": {
        "items": [
          {
            "item": "rfmod:rf_leggings"
          }
        ]
      }
    },
    "diamond_boots": {
      "trigger": "minecraft:inventory_changed",
      "conditions": {
        "items": [
          {
            "item": "rfmod:rf_boots"
          }
        ]
      }
    }
  },
  "requirements": [
    [
      "diamond_helmet",
      "diamond_chestplate",
      "diamond_leggings",
      "diamond_boots"
    ]
  ]
}